foxflow/__init__.py
foxflow/reader.py
foxflow/registry.py
foxflow/parsers/__init__.py
foxflow/parsers/ackermann_msgs/__init__.py
foxflow/parsers/ackermann_msgs/ackermann_drive.py
foxflow/parsers/custom_msgs/__init__.py
foxflow/parsers/diagnostic_msgs/__init__.py
foxflow/parsers/geometry_msgs/__init__.py
foxflow/parsers/nav_msgs/__init__.py
foxflow/parsers/sensor_msgs/__init__.py
foxflow/parsers/sensor_msgs/image.py
foxflow/parsers/sensor_msgs/imu.py
foxflow/parsers/sensor_msgs/joy.py
foxflow/parsers/sensor_msgs/laser_scan.py
foxflow/parsers/sensor_msgs/magnetic_field.py
foxflow/parsers/sensor_msgs/nav_sat_fix.py
foxflow/parsers/sensor_msgs/pointcloud2.py
foxflow/parsers/std_msgs/__init__.py
foxflow/parsers/std_msgs/arrays.py
foxflow/parsers/std_msgs/scalars.py
foxflow/parsers/trajectory_msgs/__init__.py
foxflow/parsers/visualization_msgs/__init__.py
foxflow/utils/__init__.py
foxflow/utils/images.py
foxflow/utils/sync.py
foxflow/utils/time.py
foxflow-0.1.1.dist-info/licenses/LICENSE
foxflow-0.1.1.dist-info/METADATA
foxflow-0.1.1.dist-info/WHEEL
foxflow-0.1.1.dist-info/top_level.txt
foxflow-0.1.1.dist-info/RECORD
